wind_correction/__init__.py
wind_correction/ball.py
wind_correction-0.1.3.dist-info/METADATA
wind_correction-0.1.3.dist-info/WHEEL
wind_correction-0.1.3.dist-info/RECORD
