Metadata-Version: 2.1
Name: wind-correction
Version: 0.1.3
Summary: Allows you to calculate the displacement of a falling object caused by the wind.
License: MIT
Author: Jakub Śliwka
Author-email: kubapplll@gmail.com
Requires-Python: >=3.9,<4.0
Classifier: License :: OSI Approved :: MIT License
Classifier: Programming Language :: Python :: 3
Classifier: Programming Language :: Python :: 3.9
Classifier: Programming Language :: Python :: 3.10
Classifier: Programming Language :: Python :: 3.11
Classifier: Programming Language :: Python :: 3.12
